uh2sc/__init__.py
uh2sc/abstract.py
uh2sc/constants.py
uh2sc/errors.py
uh2sc/fluid.py
uh2sc/fluidfit.py
uh2sc/ghe.py
uh2sc/main.py
uh2sc/model.py
uh2sc/salt_cavern.py
uh2sc/solvers.py
uh2sc/thermodynamics.py
uh2sc/transport.py
uh2sc/utilities.py
uh2sc/validator.py
uh2sc/well.py
uh2sc/input_schemas/ghe_schema.yml
uh2sc/input_schemas/schema_general.yml
uh2sc/input_schemas/valve_type_schema.yml
uh2sc/input_schemas/well_schema.yml
uh2sc-1.0.0.dist-info/licenses/LICENSE
uh2sc-1.0.0.dist-info/METADATA
uh2sc-1.0.0.dist-info/WHEEL
uh2sc-1.0.0.dist-info/entry_points.txt
uh2sc-1.0.0.dist-info/top_level.txt
uh2sc-1.0.0.dist-info/RECORD
