Metadata-Version: 2.4
Name: uh2sc
Version: 1.0.0
Summary: This package simulates salt caverns with hydrogen and other gas mixtures
Author-email: "Daniel L. Villa" <dlvilla@sandia.gov>
License-Expression: BSD-3-Clause
Project-URL: Homepage, https://github.com/sandialabs/uh2sc
Project-URL: Issues, https://github.com/sandialabs/uh2sc/issues
Classifier: Programming Language :: Python :: 3
Classifier: Operating System :: OS Independent
Requires-Python: >3.8
License-File: LICENSE
Requires-Dist: Cython
Requires-Dist: numpy
Requires-Dist: scipy
Requires-Dist: CoolProp
Requires-Dist: cerberus
Requires-Dist: pandas
Requires-Dist: pyyaml
Requires-Dist: rich-click
Requires-Dist: scikit-learn
Requires-Dist: joblib
Requires-Dist: matplotlib
Requires-Dist: plotly
Provides-Extra: test
Requires-Dist: pytest; extra == "test"
Requires-Dist: matplotlib; extra == "test"
Requires-Dist: py-pde; extra == "test"
Provides-Extra: docs
Requires-Dist: sphinx; extra == "docs"
Requires-Dist: furo; extra == "docs"
Requires-Dist: sphinx-autodoc-typehints; extra == "docs"
Dynamic: license-file
